{ "frames": {
   "0": {
    "frame": { "x": 0, "y": 0, "w": 16, "h": 16 },
    "rotated": false,
    "trimmed": false,
    "spriteSourceSize": { "x": 0, "y": 0, "w": 16, "h": 16 },
    "sourceSize": { "w": 16, "h": 16 },
    "duration": 100
   },
   "1": {
    "frame": { "x": 16, "y": 0, "w": 16, "h": 16 },
    "rotated": false,
    "trimmed": false,
    "spriteSourceSize": { "x": 0, "y": 0, "w": 16, "h": 16 },
    "sourceSize": { "w": 16, "h": 16 },
    "duration": 100
   },
   "2": {
    "frame": { "x": 32, "y": 0, "w": 16, "h": 16 },
    "rotated": false,
    "trimmed": false,
    "spriteSourceSize": { "x": 0, "y": 0, "w": 16, "h": 16 },
    "sourceSize": { "w": 16, "h": 16 },
    "duration": 100
   },
   "3": {
    "frame": { "x": 48, "y": 0, "w": 16, "h": 16 },
    "rotated": false,
    "trimmed": false,
    "spriteSourceSize": { "x": 0, "y": 0, "w": 16, "h": 16 },
    "sourceSize": { "w": 16, "h": 16 },
    "duration": 100
   },
   "4": {
    "frame": { "x": 64, "y": 0, "w": 16, "h": 16 },
    "rotated": false,
    "trimmed": false,
    "spriteSourceSize": { "x": 0, "y": 0, "w": 16, "h": 16 },
    "sourceSize": { "w": 16, "h": 16 },
    "duration": 100
   },
   "5": {
    "frame": { "x": 80, "y": 0, "w": 16, "h": 16 },
    "rotated": false,
    "trimmed": false,
    "spriteSourceSize": { "x": 0, "y": 0, "w": 16, "h": 16 },
    "sourceSize": { "w": 16, "h": 16 },
    "duration": 100
   },
   "6": {
    "frame": { "x": 96, "y": 0, "w": 16, "h": 16 },
    "rotated": false,
    "trimmed": false,
    "spriteSourceSize": { "x": 0, "y": 0, "w": 16, "h": 16 },
    "sourceSize": { "w": 16, "h": 16 },
    "duration": 100
   },
   "7": {
    "frame": { "x": 112, "y": 0, "w": 16, "h": 16 },
    "rotated": false,
    "trimmed": false,
    "spriteSourceSize": { "x": 0, "y": 0, "w": 16, "h": 16 },
    "sourceSize": { "w": 16, "h": 16 },
    "duration": 100
   },
   "8": {
    "frame": { "x": 128, "y": 0, "w": 16, "h": 16 },
    "rotated": false,
    "trimmed": false,
    "spriteSourceSize": { "x": 0, "y": 0, "w": 16, "h": 16 },
    "sourceSize": { "w": 16, "h": 16 },
    "duration": 100
   },
   "9": {
    "frame": { "x": 144, "y": 0, "w": 16, "h": 16 },
    "rotated": false,
    "trimmed": false,
    "spriteSourceSize": { "x": 0, "y": 0, "w": 16, "h": 16 },
    "sourceSize": { "w": 16, "h": 16 },
    "duration": 100
   },
   "10": {
    "frame": { "x": 160, "y": 0, "w": 16, "h": 16 },
    "rotated": false,
    "trimmed": false,
    "spriteSourceSize": { "x": 0, "y": 0, "w": 16, "h": 16 },
    "sourceSize": { "w": 16, "h": 16 },
    "duration": 100
   },
   "11": {
    "frame": { "x": 176, "y": 0, "w": 16, "h": 16 },
    "rotated": false,
    "trimmed": false,
    "spriteSourceSize": { "x": 0, "y": 0, "w": 16, "h": 16 },
    "sourceSize": { "w": 16, "h": 16 },
    "duration": 100
   },
   "12": {
    "frame": { "x": 192, "y": 0, "w": 16, "h": 16 },
    "rotated": false,
    "trimmed": false,
    "spriteSourceSize": { "x": 0, "y": 0, "w": 16, "h": 16 },
    "sourceSize": { "w": 16, "h": 16 },
    "duration": 100
   }
 },
 "meta": {
  "app": "http://www.aseprite.org/",
  "version": "1.2.29-x64",
  "image": "all.png",
  "format": "RGBA8888",
  "size": { "w": 208, "h": 16 },
  "scale": "1",
  "frameTags": [
   { "name": "sticky_piston_face", "from": 0, "to": 0, "direction": "forward" },
   { "name": "piston_face", "from": 1, "to": 1, "direction": "forward" },
   { "name": "piston_side", "from": 2, "to": 2, "direction": "forward" },
   { "name": "sticky_piston_side", "from": 3, "to": 3, "direction": "forward" },
   { "name": "piston_back", "from": 4, "to": 4, "direction": "forward" },
   { "name": "observer_arrow", "from": 5, "to": 5, "direction": "forward" },
   { "name": "observer_side", "from": 6, "to": 6, "direction": "forward" },
   { "name": "observer_face", "from": 7, "to": 7, "direction": "forward" },
   { "name": "observer_back", "from": 8, "to": 8, "direction": "forward" },
   { "name": "note_block", "from": 9, "to": 9, "direction": "forward" },
   { "name": "redstone_lamp_off", "from": 10, "to": 10, "direction": "forward" },
   { "name": "redstone_lamp_lit", "from": 11, "to": 11, "direction": "forward" },
   { "name": "redstone_block", "from": 12, "to": 12, "direction": "forward" }
  ],
  "layers": [
   { "name": "Layer 1", "opacity": 255, "blendMode": "normal" }
  ],
  "slices": [
  ]
 }
}
